kaag/__init__.py
kaag/analyzers/__init__.py
kaag/analyzers/base.py
kaag/analyzers/static_analyzer.py
kaag/core/__init__.py
kaag/core/kaag.py
kaag/core/norag.py
kaag/core/rag.py
kaag/dbn/__init__.py
kaag/dbn/dbn.py
kaag/gim/__init__.py
kaag/gim/gim.py
kaag/knowledge_retriever/__init__.py
kaag/knowledge_retriever/base.py
kaag/knowledge_retriever/text_file.py
kaag/llm/__init__.py
kaag/llm/base.py
kaag/llm/ollama.py
kaag/utils/__init__.py
kaag/utils/config.py
scripts/__init__.py
scripts/evaluation.py
kaag-0.1.0.dist-info/LICENSE
kaag-0.1.0.dist-info/METADATA
kaag-0.1.0.dist-info/WHEEL
kaag-0.1.0.dist-info/entry_points.txt
kaag-0.1.0.dist-info/top_level.txt
kaag-0.1.0.dist-info/RECORD
