Metadata-Version: 2.1
Name: kaag
Version: 0.1.0
Summary: Knowledge and Aptitude Augmented Generation framework
Home-page: https://github.com/aroundAI/kaag
Author: Shaurya Chaudhuri
Author-email: Shaurya Chaudhuri <shaurya@aroundai.co>
License: MIT License
Project-URL: Homepage, https://github.com/aroundAI/kaag
Classifier: Development Status :: 3 - Alpha
Classifier: Intended Audience :: Developers
Classifier: License :: OSI Approved :: MIT License
Classifier: Programming Language :: Python :: 3
Classifier: Programming Language :: Python :: 3.7
Classifier: Programming Language :: Python :: 3.8
Classifier: Programming Language :: Python :: 3.9
Requires-Python: >=3.7
License-File: LICENSE
Provides-Extra: dev
Requires-Dist: pytest; extra == "dev"
Requires-Dist: black; extra == "dev"
Requires-Dist: flake8; extra == "dev"
